flamenn/__init__.py
flamenn/errors.py
flamenn/layers.py
flamenn/networks.py
flamenn-0.1.3.dist-info/LICENSE
flamenn-0.1.3.dist-info/METADATA
flamenn-0.1.3.dist-info/WHEEL
flamenn-0.1.3.dist-info/RECORD
