Metadata-Version: 2.1
Name: flamenn
Version: 0.1.3
Summary: Flamenn is a high-level PyTorch wrapper for rapid model protyping. It uses a builder pattern for creating network arquitectures using PyTorch's components.
Home-page: https://github.com/Yoquec/flamenn
License: BSD-3-Clause
Author: Yoquec
Author-email: alvaro.viejo@pm.me
Requires-Python: >=3.8,<3.12
Classifier: License :: OSI Approved :: BSD License
Classifier: Programming Language :: Python :: 3
Classifier: Programming Language :: Python :: 3.8
Classifier: Programming Language :: Python :: 3.9
Classifier: Programming Language :: Python :: 3.10
Classifier: Programming Language :: Python :: 3.11
Requires-Dist: numpy (>=1.26.2,<2.0.0)
Requires-Dist: torch (>=2.1.2,<3.0.0)
Requires-Dist: tqdm (>=4.66.1,<5.0.0)
